djaodjin_pages-0.8.7.dist-info/licenses/LICENSE.txt
pages/__init__.py
pages/admin.py
pages/compat.py
pages/docs.py
pages/helpers.py
pages/mixins.py
pages/models.py
pages/serializers.py
pages/settings.py
pages/signals.py
pages/utils.py
pages/api/__init__.py
pages/api/assets.py
pages/api/elements.py
pages/api/newsfeed.py
pages/api/progress.py
pages/api/reactions.py
pages/api/relationship.py
pages/api/sequences.py
pages/static/js/djaodjin-pages-vue.js
pages/static/js/djaodjin-resources-vue.js
pages/templates/pages/_comments.html
pages/templates/pages/_follow_vote.html
pages/templates/pages/certificate.html
pages/templates/pages/element.html
pages/templates/pages/index.html
pages/templates/pages/editables/element.html
pages/templates/pages/editables/index.html
pages/templatetags/__init__.py
pages/templatetags/pages_tags.py
pages/urls/__init__.py
pages/urls/api/__init__.py
pages/urls/api/assets.py
pages/urls/api/editables.py
pages/urls/api/noauth.py
pages/urls/api/noauth2.py
pages/urls/api/progress.py
pages/urls/api/readers.py
pages/urls/api/sequences.py
pages/urls/views/__init__.py
pages/urls/views/editables.py
pages/urls/views/elements.py
pages/urls/views/sequences.py
pages/views/__init__.py
pages/views/elements.py
pages/views/sequences.py
djaodjin_pages-0.8.7.dist-info/METADATA
djaodjin_pages-0.8.7.dist-info/WHEEL
djaodjin_pages-0.8.7.dist-info/top_level.txt
djaodjin_pages-0.8.7.dist-info/RECORD
