Metadata-Version: 2.4
Name: djaodjin-pages
Version: 0.8.7
Summary: Django application for practices-based content
Author-email: The DjaoDjin Team <help@djaodjin.com>
Maintainer-email: The DjaoDjin Team <help@djaodjin.com>
License: BSD-2-Clause
Project-URL: repository, https://github.com/djaodjin/djaodjin-pages
Project-URL: documentation, https://djaodjin-pages.readthedocs.io/
Project-URL: changelog, https://github.com/djaodjin/djaodjin-pages/changelog
Keywords: django,cms
Classifier: Framework :: Django
Classifier: Environment :: Web Environment
Classifier: Programming Language :: Python
Classifier: License :: OSI Approved :: BSD License
Requires-Python: >=3.7
License-File: LICENSE.txt
Requires-Dist: beautifulsoup4>=4.13.4
Requires-Dist: bleach>=6.0.0
Requires-Dist: Django>=1.11
Requires-Dist: djangorestframework>=3.3.1
Requires-Dist: djaodjin-deployutils>=0.14.2
Requires-Dist: djaodjin-extended-templates>=0.4.11
Requires-Dist: html5lib>=1.1
Requires-Dist: mammoth>=1.6.0
Requires-Dist: markdownify>=0.11.6
Requires-Dist: Markdown>=3.4.4
Requires-Dist: python-dateutil>=2.8
Requires-Dist: requests>=2.22
Dynamic: license-file
